{"bcdehir":["bebreid","bebreide","bebreidede","bebreider","bede","beder","bedr","bedre","bedrede","bedrer","berber","berbere","bered","berede","bereder","beredere","beriberi","beriberier","berider","beridere","bidd","bidde","bide","bideer","biede","bier","birdie","birdier","bred","bredd","bredde","bredder","brede","bredere","breer","brei","breid","breide","breie","breiede","breier","breiere","brer","brie","brier","chic","chice","chicere","dere","deri","derre","diede","dier","dirr","dirre","dirrede","dirrer","drei","dreid","dreide","dreie","dreiede","dreier","dreiere","ebbe","ebbede","ebber","edder","edderer","eder","eide","eider","eidere","eiede","eier","eiere","eire","eirede","eirer","hebreer","hebreere","hebrider","hebridere","hedd","hedde","heddede","hedder","hede","heder","hedere","hedr","hedre","hedrede","hedrer","hehe","heie","heiede","heier","herbicid","herbicider","herd","herde","herdebred","herdebrede","herdebredere","herdebrei","herdebreie","herdede","herder","herdere","heri","herr","herre","herred","herreder","herrer","hiede","hier","hird","hirder","hire","hirer","iberer","iberere","ideer","ider","irer","irre","irrede","irrer","redd","redde","reddede","redder","reddere","rede","redede","reder","redere","rederi","rederier","reid","reide","reie","reier","reir","ribb","ribbe","ribbede","ribber","ridd","ridde","ridder","riddere","ride","rider","rier","riere"],"bcdeino":["bebo","bebodd","bebodde","beboende","bede","bedende","bedene","beende","bein","beine","beinede","beinende","beinene","bend","bende","bendende","bendene","bene","benede","benende","benene","bidd","bidde","bide","bideene","biede","bien","biende","biene","bind","binde","bindende","bindene","binne","binnen","binnene","biocid","biocidene","boben","bobene","bobin","bobinen","bobinene","bodd","bodde","boden","bodene","boen","boende","boene","boien","boiene","bonbon","bonbonen","bonbonene","bonde","bonden","bone","bonede","bonende","decenniene","denne","diede","diende","dine","diode","dioden","diodene","dobb","dobbe","dobben","dobbene","doen","doene","done","donen","donende","donene","ebbe","ebbede","ebben","ebbende","ebbene","edden","eddene","eden","edene","eene","eide","eidene","eiede","eiende","eiene","enbo","ende","enden","endende","endene","enende","eocen","eocenene","iboen","iboende","iboene","ideen","ideene","iden","idene","idoen","idoene","innbe","innbeende","innbind","innbinde","innbindende","innbo","innboene","inne","inneboende","innedo","innedoen","innedoene","innen","inni","ionene","nebb","nebbe","nebben","nebbende","nebbene","nede","nedi","neene","neid","neide","neie","neiede","neiende","neiene","nenn","nenne","nennede","nennende","neon","neonene","nibbe","nibben","nibbene","nibe","nibeende","nide","nidede","nidende","nidene","niende","niob","niobene","node","noden","nodene","noen","none","nonen","nonene","nonne","nonnen","nonnene","oboen","oboene","odde","odden","oddene","oden","odene","oiede","oiende","onde","ondene","onne","onnede","onnen","onnende","onnene"],"bcdeior":["bebo","bebodd","bebodde","beboer","beboere","bebor","bebreid","bebreide","bebreidede","bebreider","bede","beder","bedr","bedre","bedrede","bedrer","bedro","beordr","beordre","beordrede","beordrer","berber","berbere","bered","berede","bereder","beredere","beriberi","beriberier","berider","beridere","bero","berodd","berodde","beror","bidd","bidde","bide","bideer","bidro","biede","bier","biocid","biocider","birdie","birdier","bober","bodd","bodde","boder","boer","boere","boier","bord","borde","bordede","border","bore","borede","borer","borere","borre","borrer","bred","bredd","bredde","bredder","brede","bredere","breer","brei","breid","breide","breie","breiede","breier","breiere","brer","brie","brier","brobredde","brobredder","brodd","brodde","broddede","brodder","broder","brodere","broderer","broderi","broderier","broer","bror","cicero","credo","dere","deri","derre","diede","dier","diode","dioder","dirr","dirre","dirrede","dirrer","dobb","dobbe","dobber","dodre","dodrer","doer","dore","dorede","dorer","dorere","drei","dreid","dreide","dreie","dreiede","dreier","dreiere","ebbe","ebbede","ebber","edder","edderer","eder","eide","eider","eidere","eiede","eier","eiere","eire","eirede","eirer","erobr","erobre","erobrede","erobrer","erobrere","eroder","erodere","eroderer","iberer","iberere","iboer","ideer","ider","idoer","irer","irre","irrede","irrer","oboer","odde","odder","oder","odere","oiede","oier","orde","ordede","order","ordr","ordre","ordrede","ordrer","orer","orre","orrer","redd","redde","reddede","redder","reddere","rede","redede","reder","redere","rederi","rederier","reid","reide","reie","reier","reir","ribb","ribbe","ribbede","ribber","ridd","ridde","ridder","riddere","ride","rider","rier","riere","robb","robbe","robbede","robber","robbere","robe","rober","rodd","rodde","rode","rodeo","rodeoer","roder","roede","roer","roere","rorer","roro"],"bcdeiot":["bebo","bebodd","bebodde","bede","bedet","bedt","bedte","beit","beite","beitede","beitet","beitete","bete","betedd","betedde","bidd","bidde","bide","bideet","biede","biet","biete","biocid","biocidet","bite","biteti","bitetiet","bitt","bitte","bittet","bodd","bodde","boet","bote","botede","botet","botete","botid","bott","debet","dett","dette","dettede","dettet","dettete","diede","diet","diete","diett","diode","ditt","ditto","dobb","dobbe","doet","dott","dotte","dottede","dottet","dottete","ebbe","ebbede","ebbet","ebbete","eide","eidet","eiede","eiet","eiete","ette","ettid","idet","idiot","idioti","idiotiet","odde","oiede","oiet","oiete","otiet","otte","tedd","tedde","teit","teite","teitede","teitet","teitete","teodice","tete","tett","tette","tettede","tettet","tettete","tidd","tidde","tiede","tiet","tiete","tite","titid","titt","titte","tittede","tittet","tittete","tobb","tobbe","toddi","toede","toet","toete","totid","toto","tott"],"bcdelno":["bebo","bebodd","bebodde","beboende","bede","bedende","bedene","beende","belen","belene","bencelle","bencellen","bencellene","bend","bende","bendel","bendelen","bendende","bendene","bendlene","bene","benede","benende","benene","blend","blende","blendede","blenden","blendende","blendene","blod","blodcelle","blodcellen","blodcellene","blodene","blond","blonde","blonden","blondene","boben","bobene","bobl","boble","boblede","boblen","boblende","boblene","bodd","bodde","boden","bodene","boen","boende","boene","bold","bolde","bole","bolede","bolen","bolende","bolene","boll","bolle","bollede","bollen","bollende","bollene","boln","bolne","bolnede","bolnende","bonbon","bonbonen","bonbonene","bonde","bonden","bone","bonede","bonende","celle","cellen","cellene","cello","celloen","celloene","dele","delen","delende","delene","denne","dobb","dobbe","dobbel","dobben","dobbene","dobl","doble","doblede","doblende","doen","doene","dolce","done","donen","donende","donene","ebbe","ebbede","ebben","ebbende","ebbene","edden","eddene","edel","eden","edene","edle","eene","elde","eldede","elden","eldende","eldene","elede","elende","elendene","elene","elle","ellede","ellende","enbo","encellede","ende","enden","endende","endene","enecelle","enecellen","enecellene","enende","eocen","eocenene","ledd","ledde","leddede","leddende","leddene","lede","ledede","leden","ledende","ledene","leede","leende","leene","lell","lend","lende","lenden","lendende","lendene","lene","lenede","lenende","lenene","lobb","lobbe","lobbede","lobben","lobbende","lobbene","lodd","lodde","loddede","lodden","loddende","loddene","loden","lodenen","lodenene","lodne","loede","loen","loende","loene","lonen","lonene","nebb","nebbe","nebben","nebbende","nebbene","nede","neene","nenn","nenne","nennede","nennende","neon","neonene","nobel","noble","node","noden","nodene","noen","nolo","noloen","noloene","none","nonen","nonene","nonne","nonnen","nonnene","oboen","oboene","odde","odden","oddene","odel","odelen","oden","odene","odle","odlede","odlende","odlene","olen","olene","olle","ollen","ollene","onde","ondene","onne","onnede","onnen","onnende","onnene"],"bcdelnr":["bede","bedende","bedene","beder","bedr","bedre","bedrede","bedrende","bedrer","beende","belen","belene","bencelle","bencellen","bencellene","benceller","bend","bende","bendel","bendelen","bendende","bendene","bender","bendlene","bendler","bene","benede","benende","benene","bener","benere","berber","berbere","berberen","berberne","bered","berede","beredende","bereder","beredere","berederen","berederne","blend","blende","blendede","blenden","blendende","blendene","blender","blendere","blenderen","blenderende","blenderer","blenderne","bred","bredd","bredde","bredden","breddene","bredder","brede","bredere","breen","breende","breene","breer","brenn","brenne","brennende","brenner","brennere","brenneren","brennerne","brer","celeber","celebre","celebrer","celebrere","celebrerende","celebrerer","celle","cellen","cellene","celler","cendre","dele","delen","delende","delene","deler","delere","deleren","delerende","delerer","delerne","denne","dere","dernede","derre","dren","drene","drenende","drenene","drener","drenere","drenerende","drenerer","ebbe","ebbede","ebben","ebbende","ebbene","ebber","edden","eddene","edder","edderen","edderene","edderer","edel","eden","edene","eder","edle","edlere","eene","elde","eldede","elden","eldende","eldene","elder","eldre","elede","elende","elendene","elender","elene","eler","elle","ellede","ellende","eller","encellede","ende","enden","endende","endene","ender","endr","endre","endrede","endrende","endrer","enecelle","enecellen","enecellene","eneceller","enende","ener","enere","eneren","enerne","erle","erlen","erlene","erler","ledd","ledde","leddede","leddende","leddene","ledder","lede","ledede","leden","ledende","ledene","leder","ledere","lederen","lederne","leede","leende","leene","leer","lell","lend","lende","lenden","lendende","lendene","lender","lene","lenede","lenende","lenene","lener","nebb","nebbe","nebben","nebbende","nebbene","nebber","nede","nederdel","nederdelen","nederdelene","nederdeler","nederlender","nederlendere","nederlenderen","nederlenderne","nedre","neene","neer","nenn","nenne","nennede","nennende","nenner","nerd","nerden","nerdene","nerder","rebell","rebellen","rebellene","rebeller","rebellere","rebellerende","rebellerer","redd","redde","reddede","reddende","redder","reddere","redderen","redderne","rede","redede","reden","redende","redene","reder","redere","rederen","rederne","reel","reelen","reelene","reeler","reell","reelle","reende","rele","releene","releer","rendene","render","rene","renere","renn","renne","rennen","rennende","rennene","renner","rennleder","rennledere","rennlederen","rennlederne"],"bcdelor":["bebo","bebodd","bebodde","beboer","beboere","bebor","bede","beder","bedr","bedre","bedrede","bedrer","bedro","beordr","beordre","beordrede","beordrer","berber","berbere","bered","berede","bereder","beredere","bero","berodd","berodde","beror","blod","blodcelle","blodceller","bober","bobl","boble","boblede","bobler","bodd","bodde","boder","boer","boere","bold","bolde","bole","bolede","boler","bolere","bolero","boleroer","boll","bolle","bollede","boller","bord","borde","bordede","bordell","bordeller","border","bore","borede","borer","borere","borre","borrer","bred","bredd","bredde","bredder","brede","bredere","breer","brer","brobredde","brobredder","brodd","brodde","broddede","brodder","broder","brodere","broderer","broer","bror","celeber","celebre","celebrer","celebrere","celebrerer","celle","cellebro","cellebroer","celler","cello","celloer","credo","dele","deler","delere","delerer","dere","derre","dobb","dobbe","dobbel","dobber","dobl","doble","doblede","dobler","doblere","dodre","dodrer","doer","dolce","dollbord","dollborder","dore","dorede","dorer","dorere","drodl","drodle","drodlede","drodler","drodlere","ebbe","ebbede","ebber","edder","edderer","edel","eder","edle","edlere","elde","eldede","elder","eldre","elede","eler","elle","ellede","eller","erle","erler","erobr","erobre","erobrede","erobrer","erobrere","eroder","erodere","eroderer","ledd","ledde","leddede","ledder","lede","ledede","ledeord","leder","ledere","lederrolle","lederroller","leede","leer","lell","lobb","lobbe","lobbede","lobber","lodd","lodde","loddede","lodder","loddere","loede","loer","lord","lorder","oboer","odde","odder","odel","oder","odere","odle","odlede","odler","older","oldre","oldrer","oler","olle","oller","orde","ordede","order","ordr","ordre","ordrede","ordrer","orer","orre","orrer","rebell","rebeller","rebellere","rebellerer","redd","redde","reddede","redder","reddere","rede","redede","reder","redere","redobl","redoble","redoblede","redobler","reel","reeler","reell","reelle","rele","releer","reol","reoler","robb","robbe","robbede","robber","robbere","robe","rober","rodd","rodde","rode","rodel","rodeo","rodeoer","roder","rodler","roede","roer","roere","roll","rolle","rollede","roller","rorer","roro"],"bcdelot":["bebo","bebodd","bebodde","bede","bedet","bedt","bedte","belet","belt","belte","beltet","bete","betedd","betedde","betel","betl","betle","betlede","betlet","betlete","blod","blodcelle","blodet","blodete","blot","blote","blotede","blotet","blotete","blott","blotte","blottede","blottet","blottete","bobl","boble","boblede","boblet","boblete","bodd","bodde","boet","bold","bolde","boldt","bole","bolede","bolet","bolete","boll","bolle","bollede","bollet","bollete","bolt","bolte","boltede","boltet","boltete","bote","botede","botet","botete","bott","celle","cello","celt","debet","dele","delet","delt","delte","dett","dette","dettede","dettet","dettete","dobb","dobbe","dobbel","dobbelt","dobbeltcelle","dobbelte","dobl","doble","doblede","doblet","doblete","doet","dolce","dott","dotte","dottede","dottet","dottete","ebbe","ebbede","ebbet","ebbete","edel","edelt","edle","elde","eldede","eldet","eldete","elede","elet","elete","elle","ellede","ellet","ellete","elte","eltede","eltet","eltete","etle","etlede","etlet","etlete","ette","ledd","ledde","leddede","leddelt","leddelte","leddet","leddete","lede","ledede","ledet","ledete","leede","leet","leete","lell","lete","lett","lette","lettede","lettet","lettete","lobb","lobbe","lobbede","lobbet","lobbete","lodd","lodde","loddebolt","loddede","loddet","loddete","lodott","loede","loet","loete","lott","lotte","lotto","odde","odel","odle","odlede","odlet","odlete","olle","otte","tedd","tedde","tele","telede","telet","telete","tell","telle","tellede","tellet","tellete","telt","telte","teltede","teltet","teltete","tete","tett","tette","tettede","tettet","tettete","tobb","tobbe","todel","todele","todelt","todelte","toede","toet","toete","toll","tollbod","tolle","tollet","tollete","tollette","toto","tott"]}